decentralised_signing_crypto_mock/__init__.py
decentralised_signing_crypto_mock/encryption.py
decentralised_signing_crypto_mock/key_gen.py
decentralised_signing_crypto_mock/sign.py
decentralised_signing_crypto_mock-0.1.3.dist-info/METADATA
decentralised_signing_crypto_mock-0.1.3.dist-info/WHEEL
decentralised_signing_crypto_mock-0.1.3.dist-info/top_level.txt
decentralised_signing_crypto_mock-0.1.3.dist-info/RECORD
