Metadata-Version: 2.2
Name: decentralised-signing-crypto-mock
Version: 0.1.3
Summary: A mocked first version of a signature library
Home-page: 
Author: Dave Butler
Author-email: 
Classifier: Programming Language :: Python :: 3
Classifier: License :: OSI Approved :: MIT License
Classifier: Operating System :: OS Independent
Requires-Python: >=3.7
Requires-Dist: cryptography>=3.4.7
Dynamic: author
Dynamic: classifier
Dynamic: description
Dynamic: description-content-type
Dynamic: requires-dist
Dynamic: requires-python
Dynamic: summary
